<?xml  version="1.0" encoding="UTF-8"?>
<!DOCTYPE plist PUBLIC "-//Apple Computer//DTD PLIST 1.0//EN"   "http://www.apple.com/DTDs/PropertyList-1.0.dtd">
<plist version="1.0" >
<!-- Generated via Iro -->
<dict>
  <key>fileTypes</key>
  <array> 
    <string>gen</string>
   </array>
  <key>name</key>
  <string>regen</string>
  <key>patterns</key>
  <array> 
    <dict>
      <key>include</key>
      <string>#main</string>
    </dict>
   </array>
  <key>scopeName</key>
  <string>source.regen</string>
  <key>uuid</key>
  <string></string>
  <key>repository</key>
  <dict>
    <key>main</key>
    <dict>
      <key>patterns</key>
      <array> 
        <dict>
          <key>match</key>
          <string>(def|fun|if|while|for|graph|let)</string>
          <key>name</key>
          <string>keyword.regen</string>
        </dict>
        <dict>
          <key>match</key>
          <string>(\b[a-zA-Z][a-zA-Z0-9_]*)</string>
          <key>name</key>
          <string>symbol.regen</string>
        </dict>
        <dict>
          <key>include</key>
          <string>#multi_line_comment</string>
        </dict>
        <dict>
          <key>match</key>
          <string>(//.*)</string>
          <key>name</key>
          <string>comment.regen</string>
        </dict>
        <dict>
          <key>include</key>
          <string>#number</string>
        </dict>
        <dict>
          <key>begin</key>
          <string>(\{)</string>
          <key>beginCaptures</key>
          <dict>
            <key>1</key>
            <dict>
              <key>name</key>
              <string>punctuation.regen</string>
            </dict>
          </dict>
          <key>patterns</key>
          <array> 
            <dict>
              <key>include</key>
              <string>#main__1</string>
            </dict>
           </array>
          <key>end</key>
          <string>(\})</string>
          <key>endCaptures</key>
          <dict>
            <key>1</key>
            <dict>
              <key>name</key>
              <string>punctuation.regen</string>
            </dict>
          </dict>
        </dict>
        <dict>
          <key>begin</key>
          <string>(\[)</string>
          <key>beginCaptures</key>
          <dict>
            <key>1</key>
            <dict>
              <key>name</key>
              <string>punctuation.regen</string>
            </dict>
          </dict>
          <key>patterns</key>
          <array> 
            <dict>
              <key>include</key>
              <string>#main__2</string>
            </dict>
           </array>
          <key>end</key>
          <string>(\])</string>
          <key>endCaptures</key>
          <dict>
            <key>1</key>
            <dict>
              <key>name</key>
              <string>punctuation.regen</string>
            </dict>
          </dict>
        </dict>
        <dict>
          <key>begin</key>
          <string>(\()</string>
          <key>beginCaptures</key>
          <dict>
            <key>1</key>
            <dict>
              <key>name</key>
              <string>punctuation.regen</string>
            </dict>
          </dict>
          <key>patterns</key>
          <array> 
            <dict>
              <key>include</key>
              <string>#main__3</string>
            </dict>
           </array>
          <key>end</key>
          <string>(\))</string>
          <key>endCaptures</key>
          <dict>
            <key>1</key>
            <dict>
              <key>name</key>
              <string>punctuation.regen</string>
            </dict>
          </dict>
        </dict>
        <dict>
          <key>match</key>
          <string>(;|:|\+|=|&gt;|&lt;|,|\*|/)</string>
          <key>name</key>
          <string>punctuation.regen</string>
        </dict>
        <dict>
          <key>begin</key>
          <string>(\&quot;)</string>
          <key>beginCaptures</key>
          <dict>
            <key>1</key>
            <dict>
              <key>name</key>
              <string>punctuation.regen</string>
            </dict>
          </dict>
          <key>contentName</key>
          <string>text.regen</string>
          <key>end</key>
          <string>(\&quot;)</string>
          <key>endCaptures</key>
          <dict>
            <key>1</key>
            <dict>
              <key>name</key>
              <string>punctuation.regen</string>
            </dict>
          </dict>
        </dict>
        <dict>
          <key>match</key>
          <string>([^\s])</string>
          <key>name</key>
          <string>invalid.regen</string>
        </dict>
       </array>
    </dict>
    <key>main__1</key>
    <dict>
      <key>patterns</key>
      <array> 
        <dict>
          <key>include</key>
          <string>#main</string>
        </dict>
       </array>
    </dict>
    <key>main__2</key>
    <dict>
      <key>patterns</key>
      <array> 
        <dict>
          <key>include</key>
          <string>#main</string>
        </dict>
       </array>
    </dict>
    <key>main__3</key>
    <dict>
      <key>patterns</key>
      <array> 
        <dict>
          <key>include</key>
          <string>#main</string>
        </dict>
       </array>
    </dict>
    <key>main__4</key>
    <dict>
      <key>patterns</key>
      <array> 
       </array>
    </dict>
    <key>multi_line_comment</key>
    <dict>
      <key>patterns</key>
      <array> 
        <dict>
          <key>begin</key>
          <string>(/\*)</string>
          <key>beginCaptures</key>
          <dict>
            <key>1</key>
            <dict>
              <key>name</key>
              <string>comment.regen</string>
            </dict>
          </dict>
          <key>contentName</key>
          <string>comment.regen</string>
          <key>end</key>
          <string>(\*/)</string>
          <key>endCaptures</key>
          <dict>
            <key>1</key>
            <dict>
              <key>name</key>
              <string>comment.regen</string>
            </dict>
          </dict>
        </dict>
       </array>
    </dict>
    <key>multi_line_comment__1</key>
    <dict>
      <key>patterns</key>
      <array> 
       </array>
    </dict>
    <key>number</key>
    <dict>
      <key>patterns</key>
      <array> 
        <dict>
          <key>match</key>
          <string>([\x{002b}-]?([0-9]*[.])?[0-9]+f?)</string>
          <key>name</key>
          <string>constant.numeric.regen</string>
        </dict>
       </array>
    </dict>
  </dict>
</dict>
</plist>
